{
  "1": [
    "Girona vs Rayo Vallecano",
    "Villarreal vs Oviedo",
    "Mallorca vs Barcelona",
    "Alavés vs Levante",
    "Valencia vs Real Sociedad",
    "Celta Vigo vs Getafe",
    "Athletic Club vs Sevilla",
    "Espanyol vs Atlético Madrid",
    "Elche vs Betis",
    "Real Madrid vs Osasuna"
  ],
  "2": [
    "Betis vs Alavés",
    "Mallorca vs Celta Vigo",
    "Atlético Madrid vs Elche",
    "Levante vs Barcelona",
    "Osasuna vs Valencia",
    "Villarreal vs Girona",
    "Real Sociedad vs Espanyol",
    "Oviedo vs Real Madrid",
    "Athletic Club vs Rayo Vallecano",
    "Sevilla vs Getafe"
  ],
  "3": [
    "Elche vs Levante",
    "Valencia vs Getafe",
    "Alavés vs Atlético Madrid",
    "Oviedo vs Real Sociedad",
    "Girona vs Sevilla",
    "Real Madrid vs Mallorca",
    "Celta Vigo vs Villarreal",
    "Betis vs Athletic Club",
    "Espanyol vs Osasuna",
    "Rayo Vallecano vs Barcelona"
  ],
  "4": [
    "Sevilla vs Elche",
    "Getafe vs Oviedo",
    "Real Sociedad vs Real Madrid",
    "Athletic Club vs Alavés",
    "Atlético Madrid vs Villarreal",
    "Celta Vigo vs Girona",
    "Levante vs Betis",
    "Osasuna vs Rayo Vallecano",
    "Barcelona vs Valencia",
    "Espanyol vs Mallorca"
  ],
  "5": [
    "Betis vs Real Sociedad",
    "Girona vs Levante",
    "Real Madrid vs Espanyol",
    "Alavés vs Sevilla",
    "Villarreal vs Osasuna",
    "Valencia vs Athletic Club",
    "Rayo Vallecano vs Celta Vigo",
    "Mallorca vs Atlético Madrid",
    "Elche vs Oviedo",
    "Barcelona vs Getafe"
  ],
  "6": [
    "Celta Vigo vs Betis",
    "Espanyol vs Valencia",
    "Athletic Club vs Girona",
    "Sevilla vs Villarreal",
    "Levante vs Real Madrid",
    "Getafe vs Alavés",
    "Atlético Madrid vs Rayo Vallecano",
    "Real Sociedad vs Mallorca",
    "Osasuna vs Elche",
    "Oviedo vs Barcelona"
  ],
  "7": [
    "Girona vs Espanyol",
    "Getafe vs Levante",
    "Atlético Madrid vs Real Madrid",
    "Mallorca vs Alavés",
    "Villarreal vs Athletic Club",
    "Rayo Vallecano vs Sevilla",
    "Elche vs Celta Vigo",
    "Barcelona vs Real Sociedad",
    "Betis vs Osasuna",
    "Valencia vs Oviedo"
  ],
  "8": [
    "Osasuna vs Getafe",
    "Oviedo vs Levante",
    "Girona vs Valencia",
    "Athletic Club vs Mallorca",
    "Real Madrid vs Villarreal",
    "Alavés vs Elche",
    "Sevilla vs Barcelona",
    "Espanyol vs Betis",
    "Real Sociedad vs Rayo Vallecano",
    "Celta Vigo vs Atlético Madrid"
  ],
  "9": [
    "Oviedo vs Espanyol",
    "Sevilla vs Mallorca",
    "Barcelona vs Girona",
    "Villarreal vs Betis",
    "Atlético Madrid vs Osasuna",
    "Elche vs Athletic Club",
    "Celta Vigo vs Real Sociedad",
    "Levante vs Rayo Vallecano",
    "Getafe vs Real Madrid",
    "Alavés vs Valencia"
  ],
  "10": [
    "Real Sociedad vs Sevilla",
    "Girona vs Oviedo",
    "Espanyol vs Elche",
    "Athletic Club vs Getafe",
    "Valencia vs Villarreal",
    "Mallorca vs Levante",
    "Real Madrid vs Barcelona",
    "Osasuna vs Celta Vigo",
    "Rayo Vallecano vs Alavés",
    "Betis vs Atlético Madrid"
  ],
  "11": [
    "Getafe vs Girona",
    "Villarreal vs Rayo Vallecano",
    "Atlético Madrid vs Sevilla",
    "Real Sociedad vs Athletic Club",
    "Real Madrid vs Valencia",
    "Levante vs Celta Vigo",
    "Alavés vs Espanyol",
    "Barcelona vs Elche",
    "Betis vs Mallorca",
    "Oviedo vs Osasuna"
  ],
  "12": [
    "Elche vs Real Sociedad",
    "Girona vs Alavés",
    "Sevilla vs Osasuna",
    "Atlético Madrid vs Levante",
    "Espanyol vs Villarreal",
    "Athletic Club vs Oviedo",
    "Rayo Vallecano vs Real Madrid",
    "Valencia vs Betis",
    "Mallorca vs Getafe",
    "Celta Vigo vs Barcelona"
  ],
  "13": [
    "Valencia vs Levante",
    "Alavés vs Celta Vigo",
    "Barcelona vs Athletic Club",
    "Osasuna vs Real Sociedad",
    "Villarreal vs Mallorca",
    "Oviedo vs Rayo Vallecano",
    "Betis vs Girona",
    "Getafe vs Atlético Madrid",
    "Elche vs Real Madrid",
    "Espanyol vs Sevilla"
  ],
  "14": [
    "Getafe vs Elche",
    "Mallorca vs Osasuna",
    "Barcelona vs Alavés",
    "Levante vs Athletic Club",
    "Atlético Madrid vs Oviedo",
    "Real Sociedad vs Villarreal",
    "Sevilla vs Betis",
    "Celta Vigo vs Espanyol",
    "Girona vs Real Madrid",
    "Rayo Vallecano vs Valencia"
  ],
  "15": [
    "Oviedo vs Mallorca",
    "Villarreal vs Getafe",
    "Alavés vs Real Sociedad",
    "Betis vs Barcelona",
    "Athletic Club vs Atlético Madrid",
    "Elche vs Girona",
    "Valencia vs Sevilla",
    "Espanyol vs Rayo Vallecano",
    "Real Madrid vs Celta Vigo",
    "Osasuna vs Levante"
  ],
  "16": [
    "Real Sociedad vs Girona",
    "Atlético Madrid vs Valencia",
    "Mallorca vs Elche",
    "Barcelona vs Osasuna",
    "Getafe vs Espanyol",
    "Sevilla vs Oviedo",
    "Celta Vigo vs Athletic Club",
    "Levante vs Villarreal",
    "Alavés vs Real Madrid",
    "Rayo Vallecano vs Betis"
  ],
  "17": [
    "Valencia vs Mallorca",
    "Oviedo vs Celta Vigo",
    "Levante vs Real Sociedad",
    "Osasuna vs Alavés",
    "Real Madrid vs Sevilla",
    "Girona vs Atlético Madrid",
    "Villarreal vs Barcelona",
    "Elche vs Rayo Vallecano",
    "Betis vs Getafe",
    "Athletic Club vs Espanyol"
  ],
  "18": [
    "Rayo Vallecano vs Getafe",
    "Celta Vigo vs Valencia",
    "Osasuna vs Athletic Club",
    "Elche vs Villarreal",
    "Espanyol vs Barcelona",
    "Sevilla vs Levante",
    "Real Madrid vs Betis",
    "Mallorca vs Girona",
    "Alavés vs Oviedo",
    "Real Sociedad vs Atlético Madrid"
  ],
  "19": [
    "Barcelona vs Atlético Madrid",
    "Athletic Club vs Real Madrid",
    "Getafe vs Real Sociedad",
    "Oviedo vs Betis",
    "Villarreal vs Alavés",
    "Girona vs Osasuna",
    "Valencia vs Elche",
    "Rayo Vallecano vs Mallorca",
    "Levante vs Espanyol",
    "Sevilla vs Celta Vigo"
  ],
  "20": [
    "Espanyol vs Girona",
    "Real Madrid vs Levante",
    "Mallorca vs Athletic Club",
    "Osasuna vs Oviedo",
    "Betis vs Villarreal",
    "Getafe vs Valencia",
    "Atlético Madrid vs Alavés",
    "Celta Vigo vs Rayo Vallecano",
    "Real Sociedad vs Barcelona",
    "Elche vs Sevilla"
  ],
  "21": [
    "Alavés vs Betis",
    "Rayo Vallecano vs Osasuna",
    "Barcelona vs Oviedo",
    "Levante vs Elche",
    "Villarreal vs Real Madrid",
    "Sevilla vs Athletic Club",
    "Atlético Madrid vs Mallorca",
    "Girona vs Getafe",
    "Valencia vs Espanyol",
    "Real Sociedad vs Celta Vigo"
  ],
  "22": [
    "Betis vs Valencia",
    "Osasuna vs Villarreal",
    "Mallorca vs Sevilla",
    "Oviedo vs Girona",
    "Levante vs Atlético Madrid",
    "Elche vs Barcelona",
    "Athletic Club vs Real Sociedad",
    "Espanyol vs Alavés",
    "Getafe vs Celta Vigo",
    "Real Madrid vs Rayo Vallecano"
  ],
  "23": [
    "Athletic Club vs Levante",
    "Rayo Vallecano vs Oviedo",
    "Celta Vigo vs Osasuna",
    "Alavés vs Getafe",
    "Real Sociedad vs Elche",
    "Villarreal vs Espanyol",
    "Atlético Madrid vs Betis",
    "Barcelona vs Mallorca",
    "Sevilla vs Girona",
    "Valencia vs Real Madrid"
  ],
  "24": [
    "Sevilla vs Alavés",
    "Girona vs Barcelona",
    "Espanyol vs Celta Vigo",
    "Levante vs Valencia",
    "Mallorca vs Betis",
    "Elche vs Osasuna",
    "Getafe vs Villarreal",
    "Real Madrid vs Real Sociedad",
    "Oviedo vs Athletic Club",
    "Rayo Vallecano vs Atlético Madrid"
  ],
  "25": [
    "Alavés vs Girona",
    "Athletic Club vs Elche",
    "Getafe vs Sevilla",
    "Villarreal vs Valencia",
    "Real Sociedad vs Oviedo",
    "Celta Vigo vs Mallorca",
    "Atlético Madrid vs Espanyol",
    "Barcelona vs Levante",
    "Osasuna vs Real Madrid",
    "Betis vs Rayo Vallecano"
  ],
  "26": [
    "Girona vs Celta Vigo",
    "Real Madrid vs Getafe",
    "Rayo Vallecano vs Athletic Club",
    "Elche vs Espanyol",
    "Barcelona vs Villarreal",
    "Levante vs Alavés",
    "Mallorca vs Real Sociedad",
    "Betis vs Sevilla",
    "Valencia vs Osasuna",
    "Oviedo vs Atlético Madrid"
  ],
  "27": [
    "Espanyol vs Oviedo",
    "Athletic Club vs Barcelona",
    "Sevilla vs Rayo Vallecano",
    "Villarreal vs Elche",
    "Levante vs Girona",
    "Getafe vs Betis",
    "Celta Vigo vs Real Madrid",
    "Osasuna vs Mallorca",
    "Atlético Madrid vs Real Sociedad",
    "Valencia vs Alavés"
  ],
  "28": [
    "Girona vs Athletic Club",
    "Alavés vs Villarreal",
    "Mallorca vs Espanyol",
    "Barcelona vs Sevilla",
    "Oviedo vs Valencia",
    "Atlético Madrid vs Getafe",
    "Real Madrid vs Elche",
    "Rayo Vallecano vs Levante",
    "Betis vs Celta Vigo",
    "Real Sociedad vs Osasuna"
  ],
  "29": [
    "Levante vs Oviedo",
    "Barcelona vs Rayo Vallecano",
    "Sevilla vs Valencia",
    "Osasuna vs Girona",
    "Villarreal vs Real Sociedad",
    "Espanyol vs Getafe",
    "Athletic Club vs Betis",
    "Celta Vigo vs Alavés",
    "Elche vs Mallorca",
    "Real Madrid vs Atlético Madrid"
  ],
  "30": [
    "Real Sociedad vs Levante",
    "Mallorca vs Real Madrid",
    "Atlético Madrid vs Barcelona",
    "Valencia vs Celta Vigo",
    "Oviedo vs Sevilla",
    "Rayo Vallecano vs Elche",
    "Getafe vs Athletic Club",
    "Girona vs Villarreal",
    "Alavés vs Osasuna",
    "Betis vs Espanyol"
  ],
  "31": [
    "Athletic Club vs Villarreal",
    "Real Sociedad vs Alavés",
    "Mallorca vs Rayo Vallecano",
    "Celta Vigo vs Oviedo",
    "Elche vs Valencia",
    "Levante vs Getafe",
    "Osasuna vs Betis",
    "Real Madrid vs Girona",
    "Sevilla vs Atlético Madrid",
    "Barcelona vs Espanyol"
  ],
  "32": [
    "Alavés vs Mallorca",
    "Villarreal vs Celta Vigo",
    "Betis vs Real Madrid",
    "Rayo Vallecano vs Real Sociedad",
    "Valencia vs Girona",
    "Espanyol vs Levante",
    "Oviedo vs Elche",
    "Getafe vs Barcelona",
    "Atlético Madrid vs Athletic Club",
    "Osasuna vs Sevilla"
  ],
  "33": [
    "Real Madrid vs Alavés",
    "Girona vs Betis",
    "Mallorca vs Valencia",
    "Real Sociedad vs Getafe",
    "Levante vs Sevilla",
    "Athletic Club vs Osasuna",
    "Rayo Vallecano vs Espanyol",
    "Oviedo vs Villarreal",
    "Elche vs Atlético Madrid",
    "Barcelona vs Celta Vigo"
  ],
  "34": [
    "Betis vs Oviedo",
    "Espanyol vs Real Madrid",
    "Getafe vs Rayo Vallecano",
    "Sevilla vs Real Sociedad",
    "Alavés vs Athletic Club",
    "Villarreal vs Levante",
    "Girona vs Mallorca",
    "Valencia vs Atlético Madrid",
    "Celta Vigo vs Elche",
    "Osasuna vs Barcelona"
  ],
  "35": [
    "Elche vs Alavés",
    "Atlético Madrid vs Celta Vigo",
    "Sevilla vs Espanyol",
    "Mallorca vs Villarreal",
    "Athletic Club vs Valencia",
    "Levante vs Osasuna",
    "Barcelona vs Real Madrid",
    "Rayo Vallecano vs Girona",
    "Oviedo vs Getafe",
    "Real Sociedad vs Betis"
  ],
  "36": [
    "Espanyol vs Athletic Club",
    "Alavés vs Barcelona",
    "Celta Vigo vs Levante",
    "Girona vs Real Sociedad",
    "Valencia vs Rayo Vallecano",
    "Villarreal vs Sevilla",
    "Getafe vs Mallorca",
    "Osasuna vs Atlético Madrid",
    "Real Madrid vs Oviedo",
    "Betis vs Elche"
  ],
  "37": [
    "Real Sociedad vs Valencia",
    "Oviedo vs Alavés",
    "Athletic Club vs Celta Vigo",
    "Rayo Vallecano vs Villarreal",
    "Barcelona vs Betis",
    "Sevilla vs Real Madrid",
    "Elche vs Getafe",
    "Atlético Madrid vs Girona",
    "Osasuna vs Espanyol",
    "Levante vs Mallorca"
  ],
  "38": [
    "Betis vs Levante",
    "Villarreal vs Atlético Madrid",
    "Mallorca vs Oviedo",
    "Girona vs Elche",
    "Valencia vs Barcelona",
    "Espanyol vs Real Sociedad",
    "Getafe vs Osasuna",
    "Real Madrid vs Athletic Club",
    "Alavés vs Rayo Vallecano",
    "Celta Vigo vs Sevilla"
  ]
}